dria_workflows/__init__.py
dria_workflows/coder.json
dria_workflows/main2.py
dria_workflows/output.json
dria_workflows/validate.py
dria_workflows/workflows/__init__.py
dria_workflows/workflows/builder.py
dria_workflows/workflows/interface.py
dria_workflows/workflows/io.py
dria_workflows/workflows/tools/__init__.py
dria_workflows/workflows/tools/builder.py
dria_workflows/workflows/tools/parsers/__init__.py
dria_workflows/workflows/tools/parsers/base.py
dria_workflows/workflows/tools/parsers/llama.py
dria_workflows/workflows/tools/parsers/nous.py
dria_workflows/workflows/tools/parsers/openai.py
dria_workflows/workflows/w_types.py
dria_workflows/workflows/workflow.py
dria_workflows/x.py
dria_workflows-0.3.5.dist-info/METADATA
dria_workflows-0.3.5.dist-info/WHEEL
dria_workflows-0.3.5.dist-info/entry_points.txt
dria_workflows-0.3.5.dist-info/RECORD
