Metadata-Version: 2.1
Name: dria_workflows
Version: 0.3.5
Summary: Enables creation of workflows for Dria Agents
Home-page: https://github.com/firstbatchxyz/dria-workflows
License: MIT
Keywords: workflows,dria,agents,llm,ai
Author: andthattoo
Author-email: omer@firstbatch.xyz
Requires-Python: >=3.10,<4.0
Classifier: License :: OSI Approved :: MIT License
Classifier: Programming Language :: Python :: 3
Classifier: Programming Language :: Python :: 3.10
Classifier: Programming Language :: Python :: 3.11
Classifier: Programming Language :: Python :: 3.12
Requires-Dist: jsonschema (>=4.23.0,<5.0.0)
Requires-Dist: pydantic (>=2.8.2,<3.0.0)
Project-URL: Repository, https://github.com/firstbatchxyz/dria-workflows
